numcodecs_observers/__init__.py
numcodecs_observers/abc.py
numcodecs_observers/bytesize.py
numcodecs_observers/hash.py
numcodecs_observers/py.typed
numcodecs_observers/walltime.py
numcodecs_observers-0.1.2.dist-info/METADATA
numcodecs_observers-0.1.2.dist-info/WHEEL
numcodecs_observers-0.1.2.dist-info/licenses/LICENSE
numcodecs_observers-0.1.2.dist-info/RECORD
