Metadata-Version: 2.4
Name: numcodecs-observers
Version: 0.1.2
Summary: Observe encoding and decoding in the `numcodecs` buffer compression API
License: Copyright (c) 2025, Juniper Tyree
License-File: LICENSE
Requires-Python: >=3.10
Requires-Dist: numcodecs-combinators~=0.2.3
Requires-Dist: numcodecs<0.17,>=0.13.0
Requires-Dist: numpy~=2.0
Requires-Dist: typing-extensions~=4.6
